backend_gen_server/__init__.py
backend_gen_server/prompt.py
backend_gen_server/server.py
backend_gen_server/utils/__init__.py
backend_gen_server/utils/image.py
backend_gen_server/utils/ocr.py
backend_gen_server/vision/__init__.py
backend_gen_server/vision/anthropic.py
backend_gen_server/vision/cloudflare.py
backend_gen_server/vision/openai.py
backend_gen_server/vision/qwen.py
szetop_mcp_dev-0.0.1.dist-info/licenses/LICENSE
szetop_mcp_dev-0.0.1.dist-info/METADATA
szetop_mcp_dev-0.0.1.dist-info/WHEEL
szetop_mcp_dev-0.0.1.dist-info/entry_points.txt
szetop_mcp_dev-0.0.1.dist-info/top_level.txt
szetop_mcp_dev-0.0.1.dist-info/RECORD
