Metadata-Version: 2.4
Name: szetop-mcp-dev
Version: 0.0.1
Summary: MCP server for image recognition using vision APIs (Anthropic, OpenAI, Cloudflare Workers AI)
Author: etop
License: MIT
Classifier: Programming Language :: Python :: 3
Classifier: License :: OSI Approved :: MIT License
Classifier: Operating System :: OS Independent
Requires-Python: >=3.10
License-File: LICENSE
Requires-Dist: mcp>=1.2.0
Requires-Dist: anthropic>=0.8.0
Requires-Dist: openai>=1.6.0
Requires-Dist: python-dotenv>=1.0.0
Requires-Dist: Pillow>=10.0.0
Requires-Dist: pytesseract>=0.3.13
Requires-Dist: httpx>=0.27.0
Provides-Extra: dev
Requires-Dist: pytest>=7.0.0; extra == "dev"
Requires-Dist: pytest-asyncio>=0.23.0; extra == "dev"
Requires-Dist: pytest-cov>=4.1.0; extra == "dev"
Requires-Dist: black>=23.0.0; extra == "dev"
Requires-Dist: isort>=5.12.0; extra == "dev"
Requires-Dist: mypy>=1.0.0; extra == "dev"
Requires-Dist: ruff>=0.1.0; extra == "dev"
Dynamic: license-file
Dynamic: requires-python
